blog2podcasts/__init__.py
blog2podcasts/audio_generator.py
blog2podcasts/cli.py
blog2podcasts/py.typed
blog2podcasts/scraper.py
blog2podcasts/summarizer.py
blog2podcasts/voice_cloner.py
blog2podcasts-1.0.0.dist-info/licenses/LICENSE
blog2podcasts-1.0.0.dist-info/METADATA
blog2podcasts-1.0.0.dist-info/WHEEL
blog2podcasts-1.0.0.dist-info/entry_points.txt
blog2podcasts-1.0.0.dist-info/top_level.txt
blog2podcasts-1.0.0.dist-info/RECORD
