Metadata-Version: 2.4
Name: blog2podcasts
Version: 1.0.0
Summary: AI-powered tool to convert blog articles into podcast audio with optional voice cloning
Author-email: QuantBender <quantbender@users.noreply.github.com>
Maintainer-email: QuantBender <quantbender@users.noreply.github.com>
License-Expression: MIT
Project-URL: Homepage, https://github.com/QuantBender/blog2podcasts
Project-URL: Documentation, https://github.com/QuantBender/blog2podcasts#readme
Project-URL: Repository, https://github.com/QuantBender/blog2podcasts.git
Project-URL: Issues, https://github.com/QuantBender/blog2podcasts/issues
Project-URL: Changelog, https://github.com/QuantBender/blog2podcasts/blob/main/CHANGELOG.md
Keywords: podcast,blog,tts,text-to-speech,voice-cloning,ai,llm,ollama,audio,content-creation
Classifier: Development Status :: 4 - Beta
Classifier: Environment :: Console
Classifier: Intended Audience :: Developers
Classifier: Operating System :: OS Independent
Classifier: Programming Language :: Python :: 3
Classifier: Programming Language :: Python :: 3.9
Classifier: Programming Language :: Python :: 3.10
Classifier: Programming Language :: Python :: 3.11
Classifier: Programming Language :: Python :: 3.12
Classifier: Topic :: Multimedia :: Sound/Audio :: Speech
Classifier: Topic :: Internet :: WWW/HTTP :: Indexing/Search
Classifier: Topic :: Text Processing :: Linguistic
Requires-Python: >=3.9
License-File: LICENSE
Requires-Dist: trafilatura>=1.6.0
Requires-Dist: requests>=2.31.0
Requires-Dist: beautifulsoup4>=4.12.0
Requires-Dist: ollama>=0.1.0
Requires-Dist: edge-tts>=6.1.0
Requires-Dist: pydub>=0.25.1
Requires-Dist: yt-dlp>=2023.12.0
Requires-Dist: python-dotenv>=1.0.0
Requires-Dist: rich>=13.0.0
Provides-Extra: voice-cloning
Requires-Dist: TTS>=0.22.0; extra == "voice-cloning"
Provides-Extra: dev
Requires-Dist: pytest>=7.0.0; extra == "dev"
Requires-Dist: pytest-asyncio>=0.21.0; extra == "dev"
Requires-Dist: black>=23.0.0; extra == "dev"
Requires-Dist: isort>=5.12.0; extra == "dev"
Requires-Dist: flake8>=6.0.0; extra == "dev"
Requires-Dist: mypy>=1.0.0; extra == "dev"
Requires-Dist: build>=1.0.0; extra == "dev"
Requires-Dist: twine>=4.0.0; extra == "dev"
Dynamic: license-file
